MANIFEST.in
README.md
setup.py
TriacHat_2CH_Driver/SCR.py
TriacHat_2CH_Driver/__init__.py
TriacHat_2CH_Driver/config.py
cbpi4-TriacHatActor/__init__.py
cbpi4-TriacHatActor/config.yaml
cbpi4-TriacHatActor/static/cbpi.png
cbpi4-TriacHatActor/static/index.html
cbpi4-TriacHatActor/static/style.css
cbpi4_TriacHatActor.egg-info/PKG-INFO
cbpi4_TriacHatActor.egg-info/SOURCES.txt
cbpi4_TriacHatActor.egg-info/dependency_links.txt
cbpi4_TriacHatActor.egg-info/requires.txt
cbpi4_TriacHatActor.egg-info/top_level.txt