Metadata-Version: 2.1
Name: cbpi4-TriacHatActor
Version: 0.0.5
Summary: CraftBeerPi Plugin for controlling actor using Waveshare's 2CH Triac HAT for Raspberry Pi
Home-page: https://github.com/netanelklein/cbpi4-TriacHatActor
Author: Netanel Klein
Author-email: netanel@netanelk.com
License: GPLv3
Platform: UNKNOWN
